[{"id":"68672cf6-af2e-44b7-b33a-b950b58812ff","title":"Mardock Scramble: The Second Combustion 2","text":"Post-traumatic headache, unspecified, not intractable","date":1722961120000,"author":"georgerya0"},{"id":"0cd11ec6-3c94-4be8-a9d3-468addaae5bb","title":"Corn Island (Simindis kundzuli)","text":"Breakdown (mechanical) of implanted penile prosthesis, init","date":1698945941000,"author":"george.avsa"},{"id":"b13719bc-4493-42f1-99fa-17c97439a806","title":"Coming Home (Gui lai)","text":"Corrosion of first degree of left axilla, initial encounter","date":1724630734000,"author":"melster2"},{"id":"3d264f1c-c156-456f-a4f4-4e0a0f0336e7","title":"The Chase","text":"Coma scale, best verbal response, none","date":1697191809000,"author":"cbeed3"},{"id":"34810b1c-aead-4fee-9775-2d5244693b0a","title":"Fahrenheit 9/11","text":"Obstructed labor due to malposition and malpresent of fetus","date":1706738474000,"author":"pfewell4"},{"id":"4abf6200-991a-4d5a-811c-0880de77b538","title":"Ransom","text":"Puncture wound w foreign body of cheek and TMJ area","date":1709967849000,"author":"rgomersall5"},{"id":"3ddf04c5-1787-49ab-98a4-ad83eacb096a","title":"What Alice Found","text":"Partial traumatic transphalangeal amputation of other finger","date":1723498420000,"author":"rstoodley6"},{"id":"50bbba65-c1d0-4cc2-8137-73d30a4b043c","title":"And Soon the Darkness","text":"Varicos vn of r low extrem w ulc of calf and inflammation","date":1720758921000,"author":"lclowes7"},{"id":"4d9c4a06-0e67-415a-aba9-f61729327e3f","title":"Jailhouse Rock","text":"Prph T-cell lymph, not class, nodes of axilla and upper limb","date":1715451961000,"author":"cburnapp8"},{"id":"1c5d14e4-dd5b-4661-84c6-fb9ea3ba274b","title":"Falling Up 3","text":"Lorem ipsum dolor...","date":1714032314000,"author":"romeou3"},{"id":"ccd626af-4788-4aa6-9a85-02c699847c82","text":"Keklol","title":"Falling Up 3","date":1714032314000,"author":"romeou3"},{"id":"9dc7fa70-4303-4aa9-9d4e-efc448e546cb","text":"Learning node js with Dmitriy","title":"Node js","date":1725829000934,"author":"georgii"},{"id":"e3508878-e3f7-4f95-914b-f49da7c92973","title":"Node js","text":"Learning node js with Dmitriy","author":"georgii","date":1725829000934}]